flask_tasker
