Metadata-Version: 2.1
Name: Flask-Tasker
Version: 0.2.7
Summary: Simplify task management in flask applications.
Home-page: https://github.com/xuhuanstudio/flask-tasker
Author: wangqh
Author-email: 2595666958@qq.com
Classifier: Programming Language :: Python :: 3
Requires-Python: >=3.8
License-File: LICENSE
